docs/conf.py
examples/decompile_example.py
lf_pollywog-0.2.1.dist-info/licenses/LICENSE
pollywog/__init__.py
pollywog/core.py
pollywog/decomp.py
pollywog/display.py
pollywog/helpers.py
pollywog/jupyterlite_utils.py
pollywog/leapfrog_env.py
pollywog/magics.py
pollywog/patterns.py
pollywog/run.py
pollywog/utils.py
pollywog/conversion/__init__.py
pollywog/conversion/sklearn.py
tests/__init__.py
tests/conftest.py
tests/test_conversion.py
tests/test_core.py
tests/test_decomp.py
tests/test_display.py
tests/test_helpers.py
tests/test_integration.py
tests/test_jupyterlite.py
tests/test_notebooks.py
tests/test_patterns.py
tests/test_run.py
tests/test_utils.py
lf_pollywog-0.2.1.dist-info/METADATA
lf_pollywog-0.2.1.dist-info/WHEEL
lf_pollywog-0.2.1.dist-info/top_level.txt
lf_pollywog-0.2.1.dist-info/RECORD
