Metadata-Version: 2.4
Name: lf_pollywog
Version: 0.2.1
Summary: Python library for working with Leapfrog calculation sets (.lfcalc files)
Author-email: Arthur Endlein <endarthur@gmail.com>
License: MIT
Project-URL: Homepage, https://github.com/endarthur/pollywog
Project-URL: Documentation, https://pollywog.readthedocs.io
Project-URL: Repository, https://github.com/endarthur/pollywog
Project-URL: Issues, https://github.com/endarthur/pollywog/issues
Project-URL: Changelog, https://github.com/endarthur/pollywog/releases
Project-URL: Try Online, https://endarthur.github.io/pollyweb
Keywords: leapfrog,mining,geology,resource-estimation,geometallurgy,automation,geomodeling,3d-modeling,calculation-engine
Classifier: Development Status :: 4 - Beta
Classifier: Intended Audience :: Science/Research
Classifier: Intended Audience :: Developers
Classifier: Topic :: Scientific/Engineering
Classifier: Topic :: Scientific/Engineering :: GIS
Classifier: License :: OSI Approved :: MIT License
Classifier: Programming Language :: Python :: 3
Classifier: Programming Language :: Python :: 3.7
Classifier: Programming Language :: Python :: 3.8
Classifier: Programming Language :: Python :: 3.9
Classifier: Programming Language :: Python :: 3.10
Classifier: Programming Language :: Python :: 3.11
Classifier: Programming Language :: Python :: 3.12
Classifier: Operating System :: OS Independent
Requires-Python: >=3.7
License-File: LICENSE
Provides-Extra: conversion
Requires-Dist: scikit-learn; extra == "conversion"
Provides-Extra: dev
Requires-Dist: pytest; extra == "dev"
Requires-Dist: pytest-cov; extra == "dev"
Requires-Dist: scikit-learn; extra == "dev"
Requires-Dist: pandas; extra == "dev"
Requires-Dist: nbconvert>=7.0; extra == "dev"
Requires-Dist: ipykernel; extra == "dev"
Requires-Dist: pre-commit; extra == "dev"
Requires-Dist: black; extra == "dev"
Requires-Dist: ruff; extra == "dev"
Dynamic: license-file
